election_stats/__init__.py
election_stats/bar.py
election_stats/cli.py
election_stats/election.py
election_stats/heatmap.py
election_stats-0.1.0.dist-info/METADATA
election_stats-0.1.0.dist-info/WHEEL
election_stats-0.1.0.dist-info/entry_points.txt
election_stats-0.1.0.dist-info/licenses/LICENSE
election_stats-0.1.0.dist-info/RECORD
