Metadata-Version: 2.3
Name: election_stats
Version: 0.1.0
Summary: Election stats for UK General Elections
Project-URL: Repository, https://github.com/jumpingtj/election-stats
License:                     GNU AFFERO GENERAL PUBLIC LICENSE
License-File: LICENSE
Keywords: election
Classifier: Programming Language :: Python
Requires-Python: >=3.8
Requires-Dist: matplotlib
Requires-Dist: pandas
Requires-Dist: seaborn
